{
  "version": 1,
  "articles": [
    {
      "id": "architects-mission",
      "slug": "architects-mission",
      "title": "Architects Cannot Accept Collapse as an Answer",
      "titleEn": null,
      "excerpt": "When diminished conditions are repeated until they start sounding practical, collapse becomes ordinary. Architecture still matters only if it can translate crisis into new possibilities for living.",
      "body": "A great deal of daily life is now being organized by systems that ask the wrong questions. Can housing produce return? Can approvals move faster? Can construction risk be standardized? Can labor be broken down into delivery, formatting, and coordination? Can space be made easier to price, easier to repeat, easier to manage?\n\nThe questions that matter just as much are treated as secondary, unrealistic, or sentimental. Can people dwell here with dignity? Can strangers remain visible to one another? Can a neighborhood hold public life that is not immediately monetized? Can space support care, conflict, repair, and belonging instead of just circulation, extraction, and control?\n\nThat is how collapse becomes ordinary. Not only through disaster. Not only through spectacular failure. It becomes ordinary when diminished conditions are repeated until they start sounding practical. A home becomes an asset class before it becomes a home. A city becomes an engine for rent extraction before it remains a place to live. Efficiency begins to pass for intelligence. Compliance begins to pass for responsibility. Exhaustion begins to pass for realism.\n\nArchitects should reject that settlement.\n\nNot because the profession is sacred. Not because architects deserve a heroic image. But because architecture works directly on the organization of life. It shapes how people dwell, how they encounter one another, how conflict is negotiated in space, what gets shared, what gets excluded, and what kinds of futures become physically possible. If architects accept the current terms as final, they do not merely adapt to collapse. They help administer it.\n\nThe active pressures are not difficult to name. Housing is increasingly financialized: designed around debt structures, investor expectations, and yield before it is designed around living. Urban space is increasingly governed by optimization logic: throughput, legibility, surveillance, friction reduction, scalable management. Public life keeps shrinking as more of the city is privatized, securitized, priced, or reduced to circulation space with nowhere to linger. And architectural labor itself is being narrowed. More and more design work is treated as formatted delivery into systems whose priorities have already been set elsewhere: coordinate the consultants, satisfy the checklist, produce the package, move the file, reduce uncertainty, protect the timeline. In too many projects, the architect is asked to value-engineer the corridor, standardize the unit mix, clean up the presentation, and leave the underlying housing model untouched.\n\nNone of this eliminates architecture. It gives architecture a smaller job.\n\nThat smaller job is one of the profession’s two false exits. In the first, architecture becomes a packaging service for the existing order. It produces drawings faster, coordinates more smoothly, translates developer demands into cleaner visual language, and helps financialized housing or managed urban monotony arrive with less resistance. It may be technically competent. It may even be visually refined. But its intelligence is being spent on making damaged arrangements easier to deliver.\n\nThe second false exit is more flattering and just as empty. Architecture becomes critique without consequence. It identifies extraction, inequality, displacement, standardization, and ecological damage with perfect fluency. It develops a sophisticated vocabulary for ruin. But it does not move beyond diagnosis. It knows how to describe what has been lost and why. It does not accept responsibility for proposing what could be built instead.\n\nOne exit serves collapse. The other narrates it.\n\nNeither is enough. And neither deserves to be defended as realism.\n\nArchitecture still matters only if it can do something more difficult: translate crisis into new possibilities for living.\n\nThat claim has to be made plainly because the profession is under pressure to describe its value in weaker terms: authorship, image, technical expertise, coordination. Those things are real, but they are not the point. Technical tasks can be automated, subdivided, standardized, or absorbed into larger delivery systems. Documentation can be templated. Coordination can be platformized. The profession cannot base its future on protecting tasks the current economy is already trying to compress.\n\nWhat matters is harder to replace: the capacity to read a damaged situation and reorganize it spatially into something more livable.\n\nTo translate a housing crisis into a different model of dwelling.\nTo translate social isolation into a different public arrangement.\nTo translate technological change into a different structure of daily life.\nTo take conditions presented as fixed and ask what else could be organized here.\n\nAnyone can say that housing is unaffordable, that public institutions are thinning out, that the spaces most people move through every day are increasingly shaped by logistics, liability, finance, and software. The harder task is to produce another arrangement that people can actually inhabit, test, and judge.\n\nIf architects give up the right to think about how life should be organized, those decisions will not disappear. They will simply be made elsewhere: by real-estate finance deciding what counts as viable housing, by procurement models deciding what counts as feasible design, by compliance software deciding what counts as acceptable variation, by platform logic deciding what counts as friction, by security regimes deciding what counts as public order. The result will still be spatial. It will still shape daily life. It will simply do so without any serious obligation to dignity, public life, or inhabitation.\n\nThat is why the current discussion about AI and professional displacement is too narrow. The danger is not only that some tasks will be automated. The deeper danger is that architects will internalize a diminished understanding of their own work. They will begin to imagine that their highest function is to produce compliant outputs more quickly: formatted drawings, coordinated models, risk-managed packages, polished submissions. Or else they will retreat into superior commentary about the systems they no longer believe they can affect.\n\nThat would be a profound surrender.\n\nThe question is not whether architects can preserve an old monopoly. They cannot. The question is whether they still have the discipline to intervene where intervention matters: in the spatial organization of life under pressure.\n\nArchitecture is never merely procedural. A housing block, a school, a clinic, a street section, a public threshold, a shared courtyard, a retrofitted commercial shell turned into social infrastructure: these are not neutral technical outcomes. They organize access, privacy, conflict, exposure, isolation, encounter, dignity, fatigue, and belonging. They decide who is buffered and who is abandoned. They decide whether life is made thinner or made more possible.\n\nThat is why architects must continue to propose, even when certainty is unavailable.\n\nProposal is not optimism. It is not branding the future. It is the refusal to let finance models, compliance systems, and administrative metrics set the full limit of what can be built. It means acting under constraint without mistaking constraint for destiny. It means putting forward forms of housing, public space, and daily infrastructure that can be argued over precisely because they are no longer invisible.\n\nThe profession should be judged by that standard.\n\nCan it respond to financialized housing with models of dwelling that are less extractive and more collective?\nCan it respond to shrinking public life by making spaces where people are not treated only as consumers, tenants, or security variables?\nCan it respond to optimization logic by defending forms of space that allow slowness, ambiguity, encounter, and use not already predefined by management systems?\nCan it respond to the reduction of design labor into delivery and formatting by reasserting design as a way of organizing life rather than merely servicing a pipeline?\n\nIf the answer is no, then architecture has very little to defend. It will continue to exist as an industry function, but not as a serious public practice.\n\nIf the answer is yes, that value will not be proved through rhetoric about creativity or relevance. It will be proved wherever architects can still organize fragments of a more livable future before that future is guaranteed: in housing types that refuse pure financial logic, in public thresholds that create encounter instead of exclusion, in infrastructures of daily life that support dignity instead of mere throughput, in prototypes and retrofits that make another arrangement tangible and therefore arguable.\n\nThis is not an excuse for self-importance. Architecture does not become valuable by declaring itself necessary. It becomes valuable only where it refuses to confuse compliance with responsibility, efficiency with intelligence, or market realism with the limits of life.\n\nA profession that cannot do that will keep producing work. It will keep issuing drawings, details, models, packages, and approvals. It will remain busy. It may even remain prestigious. But it will have accepted a smaller purpose: to make collapse more orderly, more legible, and more professionally managed.\n\nThat is the line architects should refuse.\n\nThe standard is harder than professional survival and stricter than moral commentary. Architecture matters only where it still has the courage to identify a damaged order, refuse its terms, and give spatial form to ways of living that finance, automation, and administrative logic would not produce on their own.\n\nAnything less is not a tragic compromise. It is collaboration with the answer architects were never supposed to accept.\n",
      "weight": 3,
      "origin": "final-new",
      "sourceFile": "drafts/architects-mission.md",
      "images": [
        {
          "src": "assets/images/architects-mission/01-pexels-9405517.jpg",
          "alt": "An architect working over a blueprint at a construction site",
          "credit": "Pexels / 9405517"
        },
        {
          "src": "assets/images/architects-mission/02-pexels-8482821.jpg",
          "alt": "A construction site in progress",
          "credit": "Pexels / 8482821"
        }
      ]
    },
    {
      "id": "architectural-resolution-as-triaxial-vector",
      "slug": "architectural-resolution-as-triaxial-vector",
      "title": "Architectural Resolution as Triaxial Vector",
      "titleEn": null,
      "excerpt": "Against the scalar model — F / S / M as independent axes",
      "body": "Resolution treated as a single dial — more detail, more precision, more \"completion\" — is a weak critical instrument. It evaluates what a building looks like rather than what it does. A scalar model cannot accommodate the fact that Lebbeus Woods and Mies van der Rohe occupy the same \"low resolution\" position in conventional discourse, yet are doing entirely different things.\n\nThree axes, each independently variable: **Formal** (Articulated ↔ Diffuse, observable as joint density per m²), **Structural** (Legible ↔ Alegible, observable as legibility of the force path), and **Semantic** (Charged ↔ Mute, observable as active connotative layers).\n\nCombined, the three axes yield eight octants — from A–L–C, the Total Construct (Morphosis), and A–L–M, the Technical Sublime (Nervi), through D–L–C, the Ethical Field (Frei Otto), and D–L–M, Structural Silence (Mies), to D–A–C, Speculative Rupture (Lebbeus Woods), and D–A–M, Raw Matter.\n\nThe critical proof is D–A–C. If resolution were scalar, Woods and Mies occupy the same zone. They do not. Mies: D–L–M. Woods: D–A–C. The three axes are genuinely independent. That independence is the framework's original contribution.\n",
      "weight": 1,
      "origin": "midterm-migrated",
      "sourceFile": "architecture-garden/index.html#e1",
      "images": [
        {
          "src": "assets/images/architectural-resolution-as-triaxial-vector/01-pexels-4737237.jpg",
          "alt": "Architectural axonometric drawing on a desk",
          "credit": "Pexels / 4737237"
        },
        {
          "src": "assets/images/architectural-resolution-as-triaxial-vector/02-pexels-9616040.jpg",
          "alt": "A grid-based architectural study",
          "credit": "Pexels / 9616040"
        }
      ]
    },
    {
      "id": "the-armature-problem",
      "slug": "the-armature-problem",
      "title": "The Armature Problem",
      "titleEn": null,
      "excerpt": "When structure overwhelms the field it was built to free",
      "body": "Constant Nieuwenhuys's New Babylon (1956–74) was designed as a planet-spanning megastructure for *homo ludens* — the playing human freed from labour. Sectors were continuously reconfigurable by inhabitants. The Structural axis was deliberately Alegible. The Semantic axis was to be held open — generated by collective inhabitation over time, not authored by the architect.\n\n> Its architecture was to provide a complex armature on which could be woven endlessly new, unpredictably personal urban experiences, determined by ever-changing individual desires.\n> — Lebbeus Woods, \"Constant Vision\" (2009)\n\nBut Woods names the project's internal contradiction: the architecture of New Babylon seemed to overwhelm such playful, radical spontaneity by its sheer weight and monumental scale. This is the armature problem. The megastructure's resolution signature was too dominant. The armature could not stay mute.\n\n### The Deferring Position\n\nNew Babylon aimed for a third semantic condition: Deferring — structured to receive charge from outside, semantically open by design. The armature problem is precisely that the armature's own resolution overwhelmed this latency before inhabitants could charge it. The Deferring position requires structural and formal axes held below the threshold where they begin generating their own semantic content.",
      "weight": 1,
      "origin": "midterm-migrated",
      "sourceFile": "architecture-garden/index.html#e2",
      "images": [
        {
          "src": "assets/images/the-armature-problem/01-pexels-33998579.jpg",
          "alt": "Scaffolding at an urban construction site",
          "credit": "Pexels / 33998579"
        },
        {
          "src": "assets/images/the-armature-problem/02-pexels-14143739.jpg",
          "alt": "Exposed steel frame of a building under construction",
          "credit": "Pexels / 14143739"
        }
      ]
    },
    {
      "id": "who-assigns-the-semantic-score",
      "slug": "who-assigns-the-semantic-score",
      "title": "Who Assigns the Semantic Score?",
      "titleEn": null,
      "excerpt": "The colonial gaze as incompetence, not absence",
      "body": "The triaxial framework assumes an observer capable of counting connotative layers. But who is that observer, and what competencies do they bring? The question is not merely methodological. It is political.\n\nA vernacular building may carry extraordinary semantic density for its community — layers of genealogy, cosmological orientation, social negotiation, material memory — while registering as Raw Matter (D–A–M) on a framework calibrated to Western critical discourse. What looks like absence is illegibility. The colonial gaze mistakes its own incompetence for the building's failure.\n\n### Resolution as Market Signal\n\nDevelopers suppress Semantic resolution because it requires cultural competency to read — and cultural competency cannot be monetised efficiently. A building that means something specific to a specific community cannot be sold to everyone. The framework maps that suppression exactly.\n\nLebbeus Woods at D–A–C is already a decolonial gesture. He refuses structural legibility precisely to overload the Semantic axis. Its illegibility is not failure — it is refusal.",
      "weight": 1,
      "origin": "midterm-migrated",
      "sourceFile": "architecture-garden/index.html#e3",
      "images": [
        {
          "src": "assets/images/who-assigns-the-semantic-score/01-pexels-16942604.jpg",
          "alt": "Directional signs pointing to tourist attractions",
          "credit": "Pexels / 16942604"
        },
        {
          "src": "assets/images/who-assigns-the-semantic-score/02-pexels-17854459.jpg",
          "alt": "Multi-directional urban wayfinding signs",
          "credit": "Pexels / 17854459"
        }
      ]
    },
    {
      "id": "the-gap",
      "slug": "the-gap",
      "title": "The Gap",
      "titleEn": null,
      "excerpt": "Resolution loss between drawing and building",
      "body": "The triaxial framework was developed to measure the resolution of built things. But Lebbeus Woods dissolves the boundary between drawing and building — and reveals that the framework has been measuring the wrong thing.\n\n> I feel I'm making architecture. I believe the building comes into existence as soon as it's drawn.\n> — Lebbeus Woods\n\n> When you make a drawing — that is not a fantasy at all. That is reality.\n> — Lebbeus Woods, conversation with Raimund Abraham at La Tourette\n\n### Resolution Loss as Measurement\n\nThis gives the framework a new dimension: Resolution Loss in Translation — the gap between the F/S/M signature of the drawn architecture and the built realisation. For Woods, that gap was usually zero. For Morphosis, the built Caltrans HQ is a partial translation of a higher-resolution schema. For developer housing, the gap is maximal.\n\nWoods would say: you have described the resolution of the translation, not the resolution of the architecture. The most important critical question is not where a building sits on the cube, but how much it lost getting there.",
      "weight": 1,
      "origin": "midterm-migrated",
      "sourceFile": "architecture-garden/index.html#e4",
      "images": [
        {
          "src": "assets/images/the-gap/01-pexels-7071207.jpg",
          "alt": "A narrow alley between two buildings",
          "credit": "Pexels / 7071207"
        },
        {
          "src": "assets/images/the-gap/02-pexels-9554852.jpg",
          "alt": "A slim gap of sky between urban facades",
          "credit": "Pexels / 9554852"
        }
      ]
    },
    {
      "id": "resolution-as-commons",
      "slug": "resolution-as-commons",
      "title": "Resolution as Commons",
      "titleEn": null,
      "excerpt": "Detail as distributed permission",
      "body": "Resolution treated as an object's finish collapses into taste. Stan Allen's account of field conditions opens a different reading: resolution is not a property of an object but the behaviour of a relational matrix — porous, locally interconnected, organised less by overall shape than by internal connection rules. *Resolution belongs to the between.*\n\nOnce resolution is understood as an interface logic, it stops being synonymous with density and starts reading as governance. The question is no longer how intricate the parts are, but whether the system multiplies possible relations over time — or hardens into a single authorised configuration.\n\nCommons depends on whether the built environment is subject to collective transformation, not merely collective access. Resolution distributes agency. It decides whether users are authors or spectators.\n\n### The Assembly Test\n\nCan it be undone without cascading damage?\n\nAre its local connection rules legible to someone without specialist training?\n\nDoes it tolerate variation and improvisation?\n\nDoes it support repair and substitution over time?\n\nDoes it reserve tactical space for users — room the architect never named?\n\nWhen resolution is organised as a field of negotiable interfaces — porous, locally connected, rewriteable — it becomes commons-capable: detail as distributed permission.",
      "weight": 1,
      "origin": "midterm-migrated",
      "sourceFile": "architecture-garden/index.html#e5",
      "images": [
        {
          "src": "assets/images/resolution-as-commons/01-pexels-34886283.jpg",
          "alt": "A crowd enjoying a sunny day at an Italian-style plaza",
          "credit": "Pexels / 34886283"
        },
        {
          "src": "assets/images/resolution-as-commons/02-pexels-33689730.jpg",
          "alt": "Aerial view of people socializing in a public square",
          "credit": "Pexels / 33689730"
        }
      ]
    },
    {
      "id": "from-fragmentation-to-interface",
      "slug": "from-fragmentation-to-interface",
      "title": "From Fragmentation to Interface",
      "titleEn": null,
      "excerpt": "Keser → Koolhaas → commons — and the activating link",
      "body": "Mümün Keser's spatial fragmentation work operates at the intersection of procedural computation and speculative architecture — a generative framework where space emerges from rule-driven processes rather than fixed formal decisions. His core commitment: architects should design workflows as much as they design buildings. Every artifact is a temporal slice — a momentary resolution within a continuous field of possibility.\n\nThe OMA Maison à Bordeaux (1998) provides the crucial precedent. A hydraulic elevator platform moves vertically through openings cut in the floor slabs. At the lower level it is part of the kitchen, at mid-level it completes the living room floor, above it becomes a private study. As the platform moves, the house literally reconfigures around the occupant.\n\n> The movement of the elevator continuously changes the architecture of the house. A machine is its heart.\n> — Rem Koolhaas\n\n### The Missing Link\n\nThe theoretical trajectory — spatial fragmentation → commons/resolution → dynamic space — reaches a gap. What *activates* the transition from fragmented potential to collective spatial experience? The answer converges on interface.\n\nInterface is not a surface but a spatial condition. It is the mechanism by which resolution shifts along the spectrum — by which a boundary becomes more or less porous, by which a fragment connects to its neighbours, by which an individual encounter becomes a collective negotiation.",
      "weight": 1,
      "origin": "midterm-migrated",
      "sourceFile": "architecture-garden/index.html#e6",
      "images": [
        {
          "src": "assets/images/from-fragmentation-to-interface/01-pexels-13150081.jpg",
          "alt": "Modular facade panels on a contemporary building",
          "credit": "Pexels / 13150081"
        },
        {
          "src": "assets/images/from-fragmentation-to-interface/02-pexels-20770481.jpg",
          "alt": "Steel panel facade of a commercial building",
          "credit": "Pexels / 20770481"
        }
      ]
    },
    {
      "id": "the-space-that-watches-itself",
      "slug": "the-space-that-watches-itself",
      "title": "The Space That Watches Itself",
      "titleEn": null,
      "excerpt": "Room level — the system as narrator",
      "body": "At 06:43 the occupant's breathing pattern shifts. Not waking yet — a micro-adjustment, the body beginning its return. The room has been holding this information for seven hours alongside seventeen other variables: the CO₂ curve, the ambient temperature drift, the last recorded position of the left AirPod, the fact that the standing desk was left at 112cm when the preferred working height is 97cm, the unopened package near the entrance that has been there for four days.\n\nNone of this is surveillance. It is the condition of being a space that has decided to pay attention.\n\n### Active Infrastructure\n\nVoxal is a multi-agent spatial intelligence ecosystem. Its central claim: *space is no longer static background — it becomes active infrastructure.* Macro Agents handle room-level reconfiguration — the skeleton. Meso Agents handle furniture and functional nodes — the organs. Micro Agents handle the immediate interface between person and system — the nerve endings.\n\nThe three scales are not a product hierarchy. They are a resolution argument. Each operates at a different spatial frequency. Conflating them produces a system that cannot do any of them well.\n\n### Local Intelligence as Sovereignty\n\nThe system's intelligence is deliberately local. The household's memory of where you put the USB-C cable last Tuesday, its model of your sleep schedule — this is not data to be uploaded. It is the cognitive sediment of a life lived in a specific place. It should stay there.\n\nAt 07:12 the occupant is awake. The room has been working. The question the room cannot answer is whether this is care or something else.",
      "weight": 1,
      "origin": "midterm-migrated",
      "sourceFile": "architecture-garden/index.html#e7",
      "images": [
        {
          "src": "assets/images/the-space-that-watches-itself/01-pexels-19411622.jpg",
          "alt": "An interior with mirrored surfaces",
          "credit": "Pexels / 19411622"
        },
        {
          "src": "assets/images/the-space-that-watches-itself/02-pexels-8474278.jpg",
          "alt": "A reflective interior space",
          "credit": "Pexels / 8474278"
        }
      ]
    },
    {
      "id": "a-day-inside-a-space-that-knows-where-everything-is",
      "slug": "a-day-inside-a-space-that-knows-where-everything-is",
      "title": "A Day Inside a Space That Knows Where Everything Is",
      "titleEn": null,
      "excerpt": "Object level — the inhabitant",
      "body": "The first thing you notice is not what the space does. It is what you stop doing.\n\nYou stop the low-grade scan — the background process that runs in every human who has ever lost their keys, their charger, the specific cable that only works for that one device. In a Voxal space, the objects have been indexed. You say *I need the thing that charges the iPhone* and the system produces three candidates. The relevant Meso Agent orients toward you.\n\n### AI Furniture Logic\n\nTraditional furniture logic makes the container legible to the human. The bookshelf displays so you can scan. AI furniture logic inverts this: the container no longer needs to be legible because the system holds the index. This is a different theory of what furniture is for. What it frees is attention — quietly, in the grain of a day.\n\n### What Gets Lost\n\nThere is a competency that comes from managing your own environment: the spatial memory, the categorical thinking, the physical negotiation with your own accumulation. The knowledge the system provides is functionally equivalent to knowing yourself. The embodied relationship is not.\n\nThe friction the system removes was not only friction. Some of it was the texture of inhabitation. The space has learned you. Whether you have learned the space — that question it cannot answer.",
      "weight": 1,
      "origin": "midterm-migrated",
      "sourceFile": "architecture-garden/index.html#e8",
      "images": [
        {
          "src": "assets/images/a-day-inside-a-space-that-knows-where-everything-is/01-pexels-17536106.jpg",
          "alt": "A wall-mounted smart home automation button",
          "credit": "Pexels / 17536106"
        },
        {
          "src": "assets/images/a-day-inside-a-space-that-knows-where-everything-is/02-pexels-27638181.jpg",
          "alt": "A digital thermostat on a wall next to a window",
          "credit": "Pexels / 27638181"
        }
      ]
    },
    {
      "id": "whose-resolution-governs",
      "slug": "whose-resolution-governs",
      "title": "Whose Resolution Governs?",
      "titleEn": null,
      "excerpt": "Body level — the household",
      "body": "The Bordeaux house had one human whose movement drove the reconfiguration. Koolhaas designed the elevator for Lemoine — one body, one trajectory, one set of needs. The system was designed for a subject. The subject was singular.\n\nVoxal is designed for a household. This changes everything that the previous two entries left unasked.\n\n### The Multi-User Problem\n\nThe multi-resolution architecture handles concurrent tasks elegantly. But concurrent tasks are not the same as concurrent subjects. The system can manage a lighting query and a retrieval query simultaneously. What it cannot do cleanly is hold two people's contradictory preferences as equally valid without appointing a winner.\n\nConsider the thermal scenario: two people, different preferred temperatures, one system. Whatever algorithm resolves the conflict — average, hierarchy, whoever woke up first — that algorithm is governance. It is making a political decision about whose comfort takes precedence, dressed in the language of optimisation.\n\n### Commons or Enclosure?\n\nHigh semantic accuracy at the individual level produces low semantic openness at the collective level. The space becomes very precisely *yours* — which means it has already stopped being available to become *ours*.\n\nThe question is not whether Voxal is good or bad. The question is whether a space can be both deeply responsive and genuinely open — whether every gain in resolution at the individual level costs something at the collective one.\n\nThe garden does not know. The project continues.",
      "weight": 1,
      "origin": "midterm-migrated",
      "sourceFile": "architecture-garden/index.html#e9",
      "images": [
        {
          "src": "assets/images/whose-resolution-governs/01-pexels-16827297.jpg",
          "alt": "Buildings in the Taipei skyline",
          "credit": "Pexels / 16827297"
        },
        {
          "src": "assets/images/whose-resolution-governs/02-pexels-6875833.jpg",
          "alt": "A dense urban cityscape",
          "credit": "Pexels / 6875833"
        }
      ]
    }
  ]
}
